social_media_manager/__init__.py
social_media_manager/__main__.py
social_media_manager/py.typed
social_media_manager-0.0.1.dist-info/LICENSE
social_media_manager-0.0.1.dist-info/METADATA
social_media_manager-0.0.1.dist-info/WHEEL
social_media_manager-0.0.1.dist-info/entry_points.txt
social_media_manager-0.0.1.dist-info/RECORD
